okcolor/__init__.py
okcolor/colors.py
okcolor-1.0.2.dist-info/LICENSE
okcolor-1.0.2.dist-info/METADATA
okcolor-1.0.2.dist-info/WHEEL
okcolor-1.0.2.dist-info/top_level.txt
okcolor-1.0.2.dist-info/RECORD
