Metadata-Version: 2.1
Name: okcolor
Version: 1.0.2
Summary: Generates aesthetically pleasing RGB colors
Home-page: https://github.com/pncnmnp/okcolor
Author: Parth Parikh
Author-email: parthparikh1999p@gmail.com
Classifier: Programming Language :: Python :: 3
Classifier: License :: OSI Approved :: MIT License
Classifier: Operating System :: OS Independent
Requires-Python: >=3.6
License-File: LICENSE
Requires-Dist: Pillow
